Workbook

Sheet Data 1
A1: OrderID | B1: Date | C1: CustomerID | D1: Product | E1: Quantity | F1: UnitPrice | G1: ShippingAddress | H1: PaymentMethod | I1: OrderStatus | J1: TrackingNumber | K1: ItemsInCart | L1: CouponCode | M1: ReferralSource | N1: TotalPrice | O1: Outlier_Check
A2: ORD200000 | B2: 44930 | C2: C72649 | D2: Monitor | E2: 5 | F2: 570.62 | G2: 928 Main St | H2: Debit Card | I2: Shipped | J2: TRK37947903 | K2: 7 | L2: SAVE10 | M2: Instagram | N2: 2853.1 | O2: =IF(OR(N2<-1341.41,N2>3330.41),"Outlier","Normal") -> Normal
A3: ORD200001 | B3: 45527 | C3: C75739 | D3: Phone | E3: 2 | F3: 151.35 | G3: 823 Main St | H3: Online | I3: Shipped | J3: TRK91186779 | K3: 3 | L3: SAVE10 | M3: Referral | N3: 302.7 | O3: =IF(OR(N3<-1341.41,N3>3330.41),"Outlier","Normal") -> Normal
A4: ORD200002 | B4: 45349 | C4: C81728 | D4: Tablet | E4: 5 | F4: 550.68 | G4: 512 Main St | H4: Credit Card | I4: Cancelled | J4: TRK42903982 | K4: 8 | L4: FREESHIP | M4: Email | N4: 2753.4 | O4: =IF(OR(N4<-1341.41,N4>3330.41),"Outlier","Normal") -> Normal
A5: ORD200003 | B5: 45214 | C5: C33540 | D5: Chair | E5: 1 | F5: 273.19 | G5: 275 Main St | H5: Debit Card | I5: Returned | J5: TRK62788070 | K5: 5 | L5: SAVE10 | M5: Facebook | N5: 273.19 | O5: =IF(OR(N5<-1341.41,N5>3330.41),"Outlier","Normal") -> Normal
A6: ORD200004 | B6: 45785 | C6: C81840 | D6: Printer | E6: 4 | F6: 626.01 | G6: 668 Main St | H6: Online | I6: Delivered | J6: TRK29241424 | K6: 8 | L6: SAVE10 | M6: Email | N6: 2504.04 | O6: =IF(OR(N6<-1341.41,N6>3330.41),"Outlier","Normal") -> Normal
A7: ORD200005 | B7: 45222 | C7: C37249 | D7: Phone | E7: 2 | F7: 245.86 | G7: 934 Main St | H7: Credit Card | I7: Shipped | J7: TRK72976927 | K7: 4 | L7: SAVE10 | M7: Instagram | N7: 491.72 | O7: =IF(OR(N7<-1341.41,N7>3330.41),"Outlier","Normal") -> Normal
A8: ORD200006 | B8: 45825 | C8: C83492 | D8: Laptop | E8: 1 | F8: 664.42 | G8: 986 Main St | H8: Gift Card | I8: Returned | J8: TRK96417362 | K8: 6 | L8: SAVE10 | M8: Facebook | N8: 664.42 | O8: =IF(OR(N8<-1341.41,N8>3330.41),"Outlier","Normal") -> Normal
A9: ORD200007 | B9: 45058 | C9: C41460 | D9: Monitor | E9: 5 | F9: 149.55 | G9: 706 Main St | H9: Cash | I9: Shipped | J9: TRK78809193 | K9: 9 | L9: FREESHIP | M9: Facebook | N9: 747.75 | O9: =IF(OR(N9<-1341.41,N9>3330.41),"Outlier","Normal") -> Normal
A10: ORD200008 | B10: 45749 | C10: C26817 | D10: Phone | E10: 2 | F10: 134.28 | G10: 904 Main St | H10: Gift Card | I10: Cancelled | J10: TRK61042692 | K10: 2 | L10: No Coupon | M10: Email | N10: 268.56 | O10: =IF(OR(N10<-1341.41,N10>3330.41),"Outlier","Normal") -> Normal
A11: ORD200009 | B11: 45251 | C11: C31946 | D11: Desk | E11: 4 | F11: 509.38 | G11: 102 Main St | H11: Credit Card | I11: Shipped | J11: TRK33478363 | K11: 6 | L11: SAVE10 | M11: Google | N11: 2037.52 | O11: =IF(OR(N11<-1341.41,N11>3330.41),"Outlier","Normal") -> Normal
A12: ORD200010 | B12: 45289 | C12: C43443 | D12: Tablet | E12: 5 | F12: 625.97 | G12: 333 Main St | H12: Credit Card | I12: Returned | J12: TRK98859248 | K12: 9 | L12: WINTER15 | M12: Instagram | N12: 3129.85 | O12: =IF(OR(N12<-1341.41,N12>3330.41),"Outlier","Normal") -> Normal
A13: ORD200011 | B13: 45339 | C13: C93861 | D13: Monitor | E13: 3 | F13: 49.14 | G13: 831 Main St | H13: Online | I13: Returned | J13: TRK48234646 | K13: 7 | L13: SAVE10 | M13: Email | N13: 147.42 | O13: =IF(OR(N13<-1341.41,N13>3330.41),"Outlier","Normal") -> Normal
... A1201: ORD201199 | B1201: 45088 | C1201: C57502 | D1201: Tablet | E1201: 4 | F1201: 560.58 | G1201: 201 Main St | H1201: Gift Card | I1201: Returned | J1201: TRK51116746 | K1201: 6 | L1201: No Coupon | M1201: Referral | N1201: 2242.32 | O1201: =IF(OR(N1201<-1341.41,N1201>3330.41),"Outlier","Normal") -> Normal
L1202: =COUNTBLANK(L2:L1201) -> 0

Sheet Change LogChange ID
A1: Change ID | B1: Description | C1: Impact | D1: Status
A2: CR001 | B2: Missing values in CouponCode column filled with "No Coupon" | C2: 309 records updated — preserved data integrity instead of deleting rows | D2: Resolved
A3: CR002 | B3: Checked for duplicate OrderIDs using Remove Duplicates | C3: 0 duplicates found — dataset was already unique | D3: Verified
A4: CR003 | B4: Verified date format consistency across Date column | C4: All dates confirmed in consistent format | D4: Verified
A5: CR004 | B5: Verified TotalPrice = Quantity × UnitPrice for all rows | C5: 0 mismatches found — all calculations accurate | D5: Verified
A6: CR005 | B6: Checked text columns (Product, PaymentMethod, OrderStatus, ReferralSource) for spelling/case inconsistencies | C6: No inconsistencies found | D6: Verified

Sheet EDA_Statistics
A1: Metric | B1: Quantity | C1: UnitPrice | D1: ItemsInCart | E1: TotalPrice
A2: Mean | B2: =AVERAGE('Data 1'!E2:E1201) -> 2.9458333 | C2: =AVERAGE('Data 1'!F2:F1201) -> 356.41275 | D2: =AVERAGE('Data 1'!K2:K1201) -> 5.485 | E2: =AVERAGE('Data 1'!N2:N1201) -> 1053.9683 | G2: Q1 | H2: =QUARTILE('Data 1'!N2:N1201,1) -> 410.52
A3: Median | B3: =MEDIAN('Data 1'!E2:E1201) -> 3 | C3: =MEDIAN('Data 1'!F2:F1201) -> 364.21 | D3: =MEDIAN('Data 1'!K2:K1201) -> 5 | E3: =MEDIAN('Data 1'!N2:N1201) -> 823.615 | G3: Q3 | H3: =QUARTILE('Data 1'!N2:N1201,3) -> 1578.475
A4: Count | B4: =COUNT('Data 1'!E2:E1201) -> 1200 | C4: =COUNT('Data 1'!F2:F1201) -> 1200 | D4: =COUNT('Data 1'!K2:K1201) -> 1200 | E4: =COUNT('Data 1'!N2:N1201) -> 1200 | G4: IQR | H4: =H3-H2 -> 1167.955
A5: Max | B5: =MAX('Data 1'!E2:E1201) -> 5 | C5: =MAX('Data 1'!F2:F1201) -> 699.93 | D5: =MAX('Data 1'!K2:K1201) -> 10 | E5: =MAX('Data 1'!N2:N1201) -> 3456.4 | G5: Lower Bound | H5: =H2-(1.5*H3) -> -1957.1925
A6: Min | B6: =MIN('Data 1'!E2:E1201) -> 1 | C6: =MIN('Data 1'!F2:F1201) -> 11.39 | D6: =MIN('Data 1'!K2:K1201) -> 1 | E6: =MIN('Data 1'!N2:N1201) -> 11.39 | G6: Upper Bound | H6: =H2+(1.5*H3) -> 2778.2325
A7: Std Dev | B7: =STDEV('Data 1'!E2:E1201) -> 1.4075571 | C7: =STDEV('Data 1'!F2:F1201) -> 197.17715 | D7: =STDEV('Data 1'!K2:K1201) -> 2.2819833 | E7: =STDEV('Data 1'!N2:N1201) -> 819.85656

Sheet Pivot_ProductSales
A3: Row Labels | B3: Sum of TotalPrice | C3: Count of OrderID
A4: Chair | B4: 195620.11 | C4: 178
A5: Desk | B5: 167459.93 | C5: 170
A6: Laptop | B6: 192126.56 | C6: 173
A7: Monitor | B7: 175651.41 | C7: 163
A8: Phone | B8: 151722.39 | C8: 156
A9: Printer | B9: 195612.61 | C9: 181
A10: Tablet | B10: 186568.95 | C10: 179
A11: (blank)
A12: Grand Total | B12: 1264762 | C12: 1200

Sheet Pivot_MonthlyTrend
A3: Row Labels | B3: Sum of TotalPrice
A4: <1/1/2023
A5: (blank)
A6: 2023
A7: Jan | B7: 56685.75
A8: Feb | B8: 40117.66
A9: Mar | B9: 48609.37
A10: Apr | B10: 27751.71
A11: May | B11: 63836.84
A12: Jun | B12: 49500.19
A13: Jul | B13: 42820.66
A14: Aug | B14: 54352.14
A15: Sep | B15: 29526.67
A16: Oct | B16: 52607.85
A17: Nov | B17: 43079.67
A18: Dec | B18: 43754.73
A19: 2024
A20: Jan | B20: 38528.08
A21: Feb | B21: 36909.57
A22: Mar | B22: 36030.9
A23: Apr | B23: 49613.14
A24: May | B24: 27909.11
A25: Jun | B25: 68068.54
A26: Jul | B26: 42963.98
A27: Aug | B27: 31991.07
A28: Sep | B28: 39794.98
A29: Oct | B29: 37226.97
A30: Nov | B30: 32413.76
A31: Dec | B31: 38785.77
A32: 2025
A33: Jan | B33: 29099.4
A34: Feb | B34: 35317.55
A35: Mar | B35: 39200.66
A36: Apr | B36: 31821.2
A37: May | B37: 43396.64
A38: Jun | B38: 53047.4
A39: Grand Total | B39: 1264762

Sheet Pivot_PaymentMethod
A3: Row Labels | B3: Count of OrderID
A4: Cash | B4: 246
A5: Credit Card | B5: 234
A6: Debit Card | B6: 232
A7: Gift Card | B7: 230
A8: Online | B8: 258
A9: (blank)
A10: Grand Total | B10: 1200

Sheet Pivot_OrderStatus
A3: Row Labels | B3: Count of OrderID
A4: Cancelled | B4: 250
A5: Delivered | B5: 231
A6: Pending | B6: 237
A7: Returned | B7: 247
A8: Shipped | B8: 235
A9: (blank)
A10: Grand Total | B10: 1200

Sheet Summary
A1: Project 2: Exploratory Data Analysis (EDA) — Key Observations
A3: 1. Order Value Distribution
A4: Average (Mean) order value is $1,053.97, while the Median is $823.62. The Mean is noticeably higher than the Median, indicating a right-skewed distribution — most orders are below average, but a few high-value orders pull the average upward.
A6: 2. Best-Selling Products
A7: Chair generates the highest revenue ($195,620.11), closely followed by Printer ($195,612.61), which also has the highest order count (181 orders). Phone generates the lowest revenue ($151,722.39), showing clear variation in product performance.
A9: 3. Monthly Sales Trend
A10: June 2024 recorded the highest sales ($68,068.54), while April 2023 recorded the lowest ($27,751.71). Sales fluctuate month to month without a clear seasonal pattern, suggesting external factors (promotions, demand) drive sales more than seasonality.
A12: 4. Payment Method Preference
A13: Online payment is the most popular method (258 orders), followed by Cash (246), Credit Card (234), Debit Card (232), and Gift Card (230 — least used). Usage is fairly balanced across all payment methods.
A15: 5. Order Status Breakdown
A16: Cancelled orders are the most common (250), followed by Returned (247), Pending (237), Shipped (235), and Delivered (231 — least). The combined Cancelled/Returned count (497, ~41% of all orders) is a significant concern worth further business investigation.
A18: 6. Outliers
... A22: Sales are fairly evenly distributed across products and payment methods, but the high Cancelled/Returned rate and a handful of high-value outliers are actionable insights that warrant further investigation.
